odoo8_addon_base_location-8.0.1.0.0.99.dev12-py3.8-nspkg.pth
odoo_addons/base_location/README.rst
odoo_addons/base_location/__init__.py
odoo_addons/base_location/__openerp__.py
odoo_addons/base_location/demo/better_zip.xml
odoo_addons/base_location/i18n/base_location.pot
odoo_addons/base_location/i18n/da.po
odoo_addons/base_location/i18n/de.po
odoo_addons/base_location/i18n/es.po
odoo_addons/base_location/i18n/eu.po
odoo_addons/base_location/i18n/fi.po
odoo_addons/base_location/i18n/fr.po
odoo_addons/base_location/i18n/it.po
odoo_addons/base_location/i18n/nl.po
odoo_addons/base_location/i18n/pt_BR.po
odoo_addons/base_location/i18n/sl.po
odoo_addons/base_location/models/__init__.py
odoo_addons/base_location/models/better_zip.py
odoo_addons/base_location/models/company.py
odoo_addons/base_location/models/partner.py
odoo_addons/base_location/models/state.py
odoo_addons/base_location/security/ir.model.access.csv
odoo_addons/base_location/static/description/icon.png
odoo_addons/base_location/static/description/icon.svg
odoo_addons/base_location/views/better_zip_view.xml
odoo_addons/base_location/views/company_view.xml
odoo_addons/base_location/views/partner_view.xml
odoo_addons/base_location/views/res_country_view.xml
odoo_addons/base_location/views/state_view.xml
odoo8_addon_base_location-8.0.1.0.0.99.dev12.dist-info/METADATA
odoo8_addon_base_location-8.0.1.0.0.99.dev12.dist-info/WHEEL
odoo8_addon_base_location-8.0.1.0.0.99.dev12.dist-info/namespace_packages.txt
odoo8_addon_base_location-8.0.1.0.0.99.dev12.dist-info/top_level.txt
odoo8_addon_base_location-8.0.1.0.0.99.dev12.dist-info/RECORD
